{
	"GoodsData" : [{
			"TypeAsString":	"Espander",
			"Name": "Эспандер",
			"Health": 0,
			"Damage": 10,
			"MinExperience": 10,
			"PriceTypeAsString": "Energy",
			"PriceValue": 10
	},{
			"TypeAsString":	"Gruzilo",
			"Name": "Грузило",
			"Health": 0,
			"Damage": 20,
			"MinExperience": 20,
			"PriceTypeAsString": "Money",
			"PriceValue": 10
	},{
			"TypeAsString":	"Zazhigalka",
			"Name": "Зажигалка",
			"Health": 10,
			"Damage": 0,
			"MinExperience": 10,
			"PriceTypeAsString": "Ring",
			"PriceValue": 10
	},{
			"TypeAsString":	"Karti",
			"Name": "Карты",
			"Health": 20,
			"Damage": 0,
			"MinExperience": 20,
			"PriceTypeAsString": "Star",
			"PriceValue": 10
	}],

	"HeroSkillData": [{
			"Name": "Бомба вертикали",
			"Description": "Взрывает все элементы по вертикали",
			"TypeAsString": "BombV",
			"MinExperience": 20,
			"PriceTypeAsString": "Mobile",
			"PriceValue": 20,
			"Count": 1,
			"Experience": 1
		},{
			"Name": "Бомба горизонтали",
			"Description": "Взрывает все элементы по горизонтали",
			"TypeAsString": "BombH",
			"MinExperience": 30,
			"PriceTypeAsString": "Mobile",
			"PriceValue": 30,
			"Count": 1,
			"Experience": 1
		},{
			"Name": "Бомба по периметру",
			"Description": "Взрывает все соседние элементы",
			"TypeAsString": "BombP",
			"MinExperience": 40,
			"PriceTypeAsString": "Ring",
			"PriceValue": 40,
			"Count": 1,
			"Experience": 1
		},{
			"Name": "Бомба любой цвет",
			"Description": "Взрывает все элементы одного цвета",
			"TypeAsString": "BombC",
			"MinExperience": 50,
			"PriceTypeAsString": "Mobile",
			"PriceValue": 50,
			"Count": 1,
			"Experience": 1
		},{
			"Name": "Конвертер",
			"Description": "Меняет цвет соседних элементов",
			"TypeAsString": "Envelop",
			"MinExperience": 60,
			"PriceTypeAsString": "Mobile",
			"PriceValue": 60,
			"Experience": 1
		},{
			"Name": "Розовые очки",
			"Description": "Убрать один цвет с поля на {0} ходов",
			"TypeAsString": "ExcludeColor",
			"MinExperience": 70,
			"PriceTypeAsString": "Ring",
			"PriceValue": 70,
			"Turns": 5,
			"Experience": 2
		},{
			"Name": "Пырнуть голубя",
			"Description": "Убирает одного голубя",
			"TypeAsString": "KillEater",
			"MinExperience": 70,
			"PriceTypeAsString": "Money",
			"PriceValue": 70,
			"Experience": 1
		},{
			"Name": "Воздушка",
			"Description": "Убрать всех голубей",
			"TypeAsString": "KillAllEaters",
			"MinExperience": 70,
			"PriceTypeAsString": "Money",
			"PriceValue": 70,
			"Experience": 2
		},{
			"Name": "Задавить базаром",
			"Description": "Урон врагу {0}%",
			"TypeAsString": "Damage1",
			"Damage":	10,
			"MinExperience": 70,
			"PriceTypeAsString": "Energy",
			"PriceValue": 70,
			"Experience": 1
		},{
			"Name": "Удар с ноги ",
			"Description": "Урон врагу {0}%",
			"TypeAsString": "Damage2",
			"Damage":	100,
			"MinExperience": 70,
			"PriceTypeAsString": "Energy",
			"PriceValue": 70,
			"Experience": 2
		},{
			"Name": "Двойной удар",
			"Description": "Урон врагу {0}%",
			"TypeAsString": "Damage3",
			"Damage":	200,
			"MinExperience": 70,
			"PriceTypeAsString": "Energy",
			"PriceValue": 70,
			"Experience": 3
		},{
			"Name": "Песок в глаза",
			"Description": "Замедлить врага на {0}% на {1} ходов",
			"TypeAsString": "Slowdown1",
			"Slowdown":	50,
			"Turns": 6,
			"MinExperience": 70,
			"PriceTypeAsString": "Money",
			"PriceValue": 70,
			"Experience": 1
		},{
			"Name": "Сбить с ног",
			"Description": "Оглушает врага на {0} хода",
			"TypeAsString": "Stun1",
			"Turns": 4,
			"MinExperience": 70,
			"PriceTypeAsString": "Money",
			"PriceValue": 70,
			"Experience": 2
		},{
			"Name": "Оглушить",
			"Description": "Оглушает врага на {0} ходов",
			"TypeAsString": "Stun2",
			"Turns": 8,
			"MinExperience": 70,
			"PriceTypeAsString": "Ring",
			"PriceValue": 70,
			"Experience": 2
		},{
			"Name": "Энергия",
			"Description": "{0}% мощности, действует {1} ходов",
			"TypeAsString": "Energy",
			"Energy":	200,
			"Turns": 8,
			"MinExperience": 70,
			"PriceTypeAsString": "Ring",
			"PriceValue": 70,
			"Experience": 1
		},{
			"Name": "Неуязвимость",
			"Description": "Нулевой урон на {0} ходов",
			"TypeAsString": "Invulnerability",
			"Turns": 8,
			"MinExperience": 70,
			"PriceTypeAsString": "Ring",
			"PriceValue": 70,
			"Experience": 1
		},{
			"Name": "Лечение",
			"Description": "Востанавливает {0}% здоровья",
			"TypeAsString": "Health1",
			"Health": 30,
			"MinExperience": 0,
			"PriceTypeAsString": "Money",
			"PriceValue": 30,
			"Experience": 1
		},{
			"Name": "Супер лечение",
			"Description": "Востанавливает {0}% здоровья",
			"TypeAsString": "Health2",
			"Health": 90,
			"MinExperience": 50,
			"PriceTypeAsString": "Money",
			"PriceValue": 30,
			"Experience": 2
		}],

	"PriceData": [{
			"TypeAsString": "Energy",
			"Value":	1
		},{
			"TypeAsString": "Mobile",
			"Value":	5
		},{
			"TypeAsString": "Ring",
			"Value":	10
		},{
			"TypeAsString": "Star",
			"Value":	20
		}],

	"UserAssetsShopData": {
			"Money": [10, 20, 50, 100, 200],
			"Energy": [10, 20, 50],
			"InfinityEnergy": [4],
			"Ring": [15, 25, 50, 150, 200],
			"Mobile": [5, 10, 20, 50, 100],
			"Star": [10, 20, 50, 100, 200]
		},

	"AwardData": {
		"TileItemCollectData": [
			 {"TileItemTypeAsString": "Mobile", "AwardTypeAsString": "Mobile", "Count": 1},
			 {"TileItemTypeAsString": "Ring", "AwardTypeAsString": "Ring", "Count": 1},
			 {"TileItemTypeAsString": "Star", "AwardTypeAsString": "Star", "Count": 1},
			 {"TileItemTypeAsString": "Energy", "AwardTypeAsString": "Energy", "Count": 1},
			 {"TileItemTypeAsString": "EnemySkillSimple", "AwardTypeAsString": "Mobile", "Count":2},
			 {"TileItemTypeAsString": "EnemySkillEater", "AwardTypeAsString": "Energy", "Count": 2}
		]
	},

	"EnergyData" : {
		"IncreaseTime":	10,
		"IncreaseTimeOffline":	60,
		"MaxIncreaseCount":			30,
		"InfinityPrice": 10
	},

	"LevelFailureHelpData": {
		"Health": 3,
		"Turns":	5,
		"PriceTypeAsString":	"Money",
		"PriceValue":	50
	} 
}