{
	"Id": "1",
    "Name": "Level 4", 
    "Description": "",
	"LevelPrice": 3,
	"FightLocationTypeAsString": "Rayon5",
	"UseHeroSkill": false,
	 "TileItemDropPercent": [20, 20, 20, 20, 20],

	  "TileData": [{
			"X": 1, 
			"Y": 2, 
			"TypeAsString": "Yellow"
		},{
			"X": 1, 
			"Y": 1, 
			"TypeAsString": "Blue"
		},{
			"X": 2, 
			"Y": 0, 
			"TypeAsString": "Green"
		},{
			"X": 1, 
			"Y": 0, 
			"TypeAsString": "Red"
		},{
			"X": 1, 
			"Y": 3, 
			"TypeAsString": "Green"
		},{
			"X": 2, 
			"Y": 1, 
			"TypeAsString": "Green"
		},{
			"X": 2, 
			"Y": 2, 
			"TypeAsString": "Green"
		},{
			"X": 1, 
			"Y": 4, 
			"TypeAsString": "Yellow"
		},{
			"X": 0, 
			"Y": 0, 
			"TypeAsString": "Blue"
		},{
			"X": 0, 
			"Y": 1, 
			"TypeAsString": "Red"
		},{
			"X": 0, 
			"Y": 2, 
			"TypeAsString": "Yellow"
		},{
			"X": 0, 
			"Y": 3, 
			"TypeAsString": "Yellow"
		},{
			"X": 0, 
			"Y": 4, 
			"TypeAsString": "Blue"
		},{
			"X": 2, 
			"Y": 3, 
			"TypeAsString": "Blue"
		},{
			"X": 2, 
			"Y": 4, 
			"TypeAsString": "Red"
		},{
			"X": 3, 
			"Y": 0, 
			"TypeAsString": "Purple"
		},{
			"X": 3, 
			"Y": 1, 
			"TypeAsString": "Red"
		},{
			"X": 3, 
			"Y": 2, 
			"TypeAsString": "Yellow"
		},{
			"X": 3, 
			"Y": 3, 
			"TypeAsString": "Yellow"
		},{
			"X": 3, 
			"Y": 4, 
			"TypeAsString": "Green"
		},{
			"X": 4, 
			"Y": 0, 
			"TypeAsString": "Red"
		},{
			"X": 4, 
			"Y": 1, 
			"TypeAsString": "BombV"
		},{
			"X": 5, 
			"Y": 0, 
			"TypeAsString": "Purple"
		},{
			"X": 5, 
			"Y": 1, 
			"TypeAsString": "Blue"
		},{
			"X": 6, 
			"Y": 0, 
			"TypeAsString": "Purple"
		},{
			"X": 6, 
			"Y": 1, 
			"TypeAsString": "Green"
		}],
	
	  "BarrierData": [{
            "X1": 0, 
            "Y1": 0, 
            "X2": 1, 
            "Y2": 0, 
            "TypeAsString": "Barrier_2",
						"Health": 2
        }, {
            "X1": 0, 
            "Y1": 1, 
            "X2": 1, 
            "Y2": 1, 
            "TypeAsString": "Barrier_2",
						"Health": 1
        },{
            "X1": 0, 
            "Y1": 0, 
            "X2": 0, 
            "Y2": 1, 
            "TypeAsString": "Barrier_1"
        },  {
            "X1": 0, 
            "Y1": 2, 
            "X2": 1, 
            "Y2": 2, 
            "TypeAsString": "Barrier_2"
        }, {
            "X1": 2, 
            "Y1": 2, 
            "X2": 2, 
            "Y2": 3, 
            "TypeAsString": "Barrier_1"
        },{
            "X1": 4, 
            "Y1": 2, 
            "X2": 4, 
            "Y2": 3, 
            "TypeAsString": "Barrier_1"
        }, {
            "X1": 5, 
            "Y1": 2, 
            "X2": 5, 
            "Y2": 3, 
            "TypeAsString": "Barrier_2"
        }, {
            "X1": 6, 
            "Y1": 4, 
            "X2": 6, 
            "Y2": 5, 
            "TypeAsString": "Barrier_2"
        }, {
            "X1": 4, 
            "Y1": 5, 
            "X2": 5, 
            "Y2": 5, 
            "TypeAsString": "Barrier_1"
        }], 
		
   "TargetData": [{
		"Count": 10, 
		"TypeAsString": "Green"
	}, {
		"Count": 10, 
		"TypeAsString": "Purple"
	},{
		"Count": 10, 
		"TypeAsString": "Blue"
	}],
		

	"EnemyData": {
		"Health": 80,
		"Damage": 8,
		"SkillRatio": 1,
		"SkillData": [{
				"TypeAsString": "Eater",
				"Count": 2
			},{
				"TypeAsString": "Slime",
				"Count": 2,
				"Health": 1
			},{
				"TypeAsString": "Simple",
				"Count": 2
			}]
	},

	"AutoDropData" : [{
		"Ratio": 20,
		"TileItem" : { "TypeAsString": "Mobile" }
	},{
		"Ratio": 20,
		"TileItem" : { "TypeAsString": "Ring" }
	},{
		"Ratio": 1,
		"TileItem" : { "TypeAsString": "Star" }
	},{
		"Ratio": 20,
		"TileItem" : { "TypeAsString": "Energy" }
	}],


	"SuccessAwardData": {
		"Experience": 10,
		"UserAssets": [
		 {"TypeAsString": "Energy", "Value":	2},
		 {"TypeAsString": "Mobile", "Value":	1},
		 {"TypeAsString": "Ring", "Value":	5},
		 {"TypeAsString": "Star", "Value":	1}
		]
	},

	"FailureAwardData": {
		"Experience": 0,
		"UserAssets": [
		 {"TypeAsString": "Energy", "Value":	1},
		 {"TypeAsString": "Mobile", "Value":	2},
		 {"TypeAsString": "Ring", "Value":	1}
		]
	},

	"EducationData": {
		"Steps": [{
			"Description": "Собирай цепочки, чтобы увеличивать мощность и наносить урон врагу",
			"DescriptionOffset": {"x": 1.5, "y": 1.5},
			"TypeAsString": "Collect",
			"Positions1": [{"x": 1, "y": 3}, {"x": 2, "y": 2}, {"x": 2, "y": 1}, {"x": 2, "y": 0}],
			"ArrowGameObjectName": "HeroProgressText",
			"ArrowOffset": {"x": 0, "y": 0.3},
			"ShowCloseButton": false,
			"ArrowAngle": -30,
			"StartNextStepOnNext": false
		},{
			"Description": "Урон наносимый врагу равен твоей силе",
			"DescriptionOffset": {"x": 2, "y": 1.8},
			"TypeAsString": "Info",
			"ArrowGameObjectName": "HeroDamageText",
			"ArrowOffset": {"x": 0, "y": -0.1},
			"ShowCloseButton": true,
			"ArrowAngle": 200,
			"StartNextStepOnNext": true
		},{
			"Description": "Не забывай следить за своим здоровьем",
			"DescriptionOffset": {"x": 2, "y": 1.8},
			"TypeAsString": "Info",
			"ArrowGameObjectName": "HeroHealthText",
			"ArrowOffset": {"x": 0, "y": -0.1},
			"ShowCloseButton": true,
			"ArrowAngle": 200,
			"StartNextStepOnNext": true
		}]
	}


}